simple_system_tests/CachedLogger.py
simple_system_tests/CommandLineParser.py
simple_system_tests/ExitHooks.py
simple_system_tests/ReportHtml.py
simple_system_tests/TestCase.py
simple_system_tests/TestResult.py
simple_system_tests/TestSuite.py
simple_system_tests/__init__.py
simple_system_tests/helper.py
simple_system_tests-0.6.2.dist-info/LICENSE
simple_system_tests-0.6.2.dist-info/METADATA
simple_system_tests-0.6.2.dist-info/WHEEL
simple_system_tests-0.6.2.dist-info/top_level.txt
simple_system_tests-0.6.2.dist-info/RECORD
