Metadata-Version: 2.1
Name: simple-system-tests
Version: 0.6.2
Summary: Simple System Tests Environment.
Home-page: https://github.com/chrisKoeh/simple-system-tests
Author: Christian Koehler
Author-email: christian_koehler87@gmx.de
License: MIT
Platform: UNKNOWN
Requires-Python: >=3.5
